perses-0.0.2.dist-info/METADATA
perses-0.0.2.dist-info/WHEEL
perses-0.0.2.dist-info/entry_points.txt
perses-0.0.2.dist-info/licenses/LICENSE
perses/__init__.py
perses/model/__init__.py
perses/model/common.py
perses/model/dashboard.py
perses/model/panel.py
perses/model/project.py
perses/model/query.py
perses/model/user.py
perses/model/variable.py
perses/py.typed
perses-0.0.2.dist-info/RECORD
